<?xml version='1.0' encoding='utf-8'?>
<hkbno>
	<area>
		<name>東南亞</name>
		<country>
			<name>日本</name>
			<image>images/location/japan.jpg</image>
			<visa>不須辦簽証</visa>
			<detail>hkbno/japan.html</detail>
		</country>
		<country>
			<name>韓國</name>
			<image>images/location/korea.jpg</image>
			<visa>不須辦簽証</visa>
			<detail>hkbno/korea.html</detail>
		</country>
		<country>
			<name>台灣</name>
			<image>images/location/taiwan.jpg</image>
			<visa>須辦簽証</visa>
			<detail>hkbno/taiwan.html</detail>
		</country>
		<country>
			<name>泰國</name>
			<image>images/location/thailand.jpg</image>
			<visa>不須辦簽証</visa>
			<detail>hkbno/thailand.html</detail>
		</country>
		<country>
			<name>馬來西亞</name>
			<image>images/location/malaysia.jpg</image>
			<visa>不須辦簽証</visa>
			<detail>hkbno/malaysia.html</detail>
		</country>
		<country>
			<name>星加坡</name>
			<image>images/location/singapore.jpg</image>
			<visa>不須辦簽証</visa>
			<detail>hkbno/singapore.html</detail>
		</country>
		<country>
			<name>越南</name>
			<image>images/location/vietnam.jpg</image>
			<visa>須辦簽証</visa>
			<detail>hkbno/vietnam.html</detail>
		</country>
		<country>
			<name>汶萊</name>
			<image>images/location/brunei.jpg</image>
			<visa>須辦簽証</visa>
			<detail>hkbno/brunei.html</detail>
		</country>
	</area>

	<area>
		<name>地中海</name>
		<country>
			<name>杜拜</name>
			<image>images/location/dubai.jpg</image>
			<visa>須辦簽証</visa>
			<detail>hkbno/dubai.html</detail>
		</country>
		<country>
			<name>埃及</name>
			<image>images/location/egypt.jpg</image>
			<visa>須辦簽証</visa>
			<detail>hkbno/egypt.html</detail>
		</country>
		<country>
			<name>希臘</name>
			<image>images/location/greece.jpg</image>
			<visa>不須辦簽証</visa>
			<detail>hkbno/greece.html</detail>
		</country>
		<country>
			<name>土耳其</name>
			<image>images/location/turkey.jpg</image>
			<visa>須辦簽証</visa>
			<detail>hkbno/turkey.html</detail>
		</country>
	</area>
	
	<area>
		<name>中東</name>
		<country>
			<name>印度</name>
			<image>images/location/india.jpg</image>
			<visa>須辦簽証</visa>
			<detail>hkbno/india.html</detail>
		</country>
	</area>
	
	<area>
		<name>歐洲</name>
		<country>
			<name>法國</name>
			<image>images/location/france.jpg</image>
			<visa>不須辦簽証</visa>
			<detail>hkbno/france.html</detail>
		</country>
		
		<country>
			<name>奧地利</name>
			<image>images/location/austria.jpg</image>
			<visa>不須辦簽証</visa>
			<detail>hkbno/austria.html</detail>
		</country>
		
		<country>
			<name>德國</name>
			<image>images/location/germany.jpg</image>
			<visa>不須辦簽証</visa>
			<detail>hkbno/germany.html</detail>
		</country>
		
		<country>
			<name>俄羅斯</name>
			<image>images/location/russia.jpg</image>
			<visa>須辦簽証</visa>
			<detail>hkbno/russia.html</detail>
		</country>
	</area>
	
	<area>
		<name>澳紐</name>
		<country>
			<name>澳洲</name>
			<image>images/location/australia.jpg</image>
			<visa>須辦簽証</visa>
			<detail>hkbno/australia.html</detail>
		</country>
	</area>
	
	<area>
		<name>美加</name>
		<country>
			<name>關島</name>
			<image>images/location/guam.jpg</image>
			<visa>須辦簽証</visa>
			<detail>hkbno/guam.html</detail>
		</country>
	</area>
</hkbno>